pyjavaz/__init__.py
pyjavaz/_version.py
pyjavaz/bridge.py
pyjavaz/example.py
pyjavaz/wrappers.py
pyjavaz-1.2.8.dist-info/LICENSE
pyjavaz-1.2.8.dist-info/METADATA
pyjavaz-1.2.8.dist-info/WHEEL
pyjavaz-1.2.8.dist-info/top_level.txt
pyjavaz-1.2.8.dist-info/RECORD
